wordlepy/__init__.py
wordlepy/frequency_list.xlsx
wordlepy/wordle_class.py
wordlepy/wordle_solutions.txt
wordlepy/wordle_utils.py
wordlepy/wordlebot.py
wordlepy/words_alpha.txt
wordlepy-1.6.dist-info/LICENSE
wordlepy-1.6.dist-info/METADATA
wordlepy-1.6.dist-info/WHEEL
wordlepy-1.6.dist-info/top_level.txt
wordlepy-1.6.dist-info/RECORD
