Metadata-Version: 2.1
Name: wordlepy
Version: 1.6
Summary: python wordle utilities
Author: Ben Hook
Author-email: benahook@gmail.com
License: GNU
Platform: UNKNOWN
Classifier: Development Status :: 4 - Beta
Classifier: Environment :: Console
Classifier: Intended Audience :: End Users/Desktop
Classifier: License :: Freeware
Classifier: Operating System :: OS Independent
Classifier: Programming Language :: Cython
Classifier: Programming Language :: Python
Classifier: Programming Language :: Python :: 3
Classifier: Topic :: Games/Entertainment
Requires-Python: >=3.6
License-File: LICENSE
Requires-Dist: pandas
Requires-Dist: openpyxl
Requires-Dist: selenium
